{
    "Bio": "An NRI and his wife decide to stay in his ancestral home, paying no heed to the warnings about ghosts. Soon, inexplicable occurrences cause him to call a psychiatrist to help solve the mystery.",
    "Cast": [
        {
            "IMDB_ids": "nm0474774",
            "Name": "Akshay Kumar"
        },
        {
            "IMDB_ids": "nm1799038",
            "Name": "Vidya Balan"
        },
        {
            "IMDB_ids": "nm1832004",
            "Name": "Shiney Ahuja"
        },
        {
            "IMDB_ids": "nm0665349",
            "Name": "Ameesha Patel"
        },
        {
            "IMDB_ids": "nm0712546",
            "Name": "Paresh Rawal"
        },
        {
            "IMDB_ids": "nm1056425",
            "Name": "Rajpal Yadav"
        },
        {
            "IMDB_ids": "nm2147526",
            "Name": "Asrani"
        },
        {
            "IMDB_ids": "nm0324845",
            "Name": "Vikram Gokhale"
        },
        {
            "IMDB_ids": "nm1259084",
            "Name": "Manoj Joshi"
        },
        {
            "IMDB_ids": "nm1671375",
            "Name": "Rasika Joshi"
        },
        {
            "IMDB_ids": "nm2537606",
            "Name": "Tarina Patel"
        },
        {
            "IMDB_ids": "nm5434905",
            "Name": "Jimit Trivedi"
        },
        {
            "IMDB_ids": "nm0898913",
            "Name": "Vineeth"
        }
    ],
    "Country": "India",
    "Director": [
        "Priyadarshan"
    ],
    "Genres": [
        " Comedy",
        " Horror",
        " Mystery",
        " Thriller"
    ],
    "Language": [
        "Hindi",
        "Bengali"
    ],
    "Movie Title": "Bhool Bhulaiyaa ",
    "Poster_image_url": "https://m.media-amazon.com/images/M/MV5BN2Q1ODU2NzQtMDE4Mi00M2ViLTg5NmItYWNlMzBmMDdjNGY0XkEyXkFqcGdeQXVyODE5NzE3OTE@._V1_UX182_CR0,0,182,268_AL__QL50.jpg",
    "RunTime": "159min"
}